grpc_contracts/__init__.py
grpc_contracts/training_pb2.py
grpc_contracts/training_pb2_grpc.py
grpc_contracts-0.1.0.dist-info/licenses/LICENSE.txt
grpc_contracts-0.1.0.dist-info/METADATA
grpc_contracts-0.1.0.dist-info/WHEEL
grpc_contracts-0.1.0.dist-info/top_level.txt
grpc_contracts-0.1.0.dist-info/RECORD
